README.txt
setup.py
collective/__init__.py
collective.remove.kupu.egg-info/PKG-INFO
collective.remove.kupu.egg-info/SOURCES.txt
collective.remove.kupu.egg-info/dependency_links.txt
collective.remove.kupu.egg-info/entry_points.txt
collective.remove.kupu.egg-info/namespace_packages.txt
collective.remove.kupu.egg-info/not-zip-safe
collective.remove.kupu.egg-info/requires.txt
collective.remove.kupu.egg-info/top_level.txt
collective/remove/__init__.py
collective/remove/kupu/__init__.py
collective/remove/kupu/configure.zcml
collective/remove/kupu/profiles/default/cssregistry.xml
collective/remove/kupu/profiles/default/jsregistry.xml
collective/remove/kupu/profiles/default/metadata.xml
collective/remove/kupu/profiles/default/propertiestool.xml
docs/HISTORY.txt