Metadata-Version: 1.0
Name: collective.remove.kupu
Version: 0.1
Summary: Remove kupu from Plone
Home-page: http://svn.plone.org/svn/collective/collective.remove/kupu
Author: JeanMichel FRANCOIS
Author-email: jeanmichel.francois@makina-corpus.org
License: GPL
Platform: UNKNOWN
Classifier: Programming Language :: Python
